{
  "title": "关于开展全国煤电机组改造升级的通知",
  "doc_no": "发改运行〔2021〕1519号",
  "issuing_body": "国家发展改革委/国家能源局",
  "signed_date": "2021-11-03",
  "published_date": "2021-11-03",
  "category": "56_电力行业碳达峰碳中和、绿色低碳转型、节能降碳与循环经济",
  "official_html_url": "https://www.ndrc.gov.cn/xxgk/zcfb/tz/202111/t20211103_1302856.html",
  "official_pdf_url": "",
  "status": "ok",
  "method": "delivery_v3_browser_print_pdf",
  "capture_profile": "delivery_v3_browser_print_pdf",
  "crop_top_px": 0,
  "anchor_selector": "",
  "direct_pdf_error": "",
  "error": "",
  "generated_at": "2026-04-27T18:47:15.415026",
  "pdf_path": "/Users/mf/.openclaw/workspace/knowledge-base/政策监控/戴总的政策文件（60部分清单）/56_电力行业碳达峰碳中和、绿色低碳转型、节能降碳与循环经济/pdf/2021-11-03_发改运行〔2021〕1519号_关于开展全国煤电机组改造升级的通知.pdf",
  "screenshot_path": "",
  "markdown_path": "",
  "size_bytes": 269141,
  "sha1": "896b370ff8be56b87a5a5adc90e620ff839c7db4",
  "synced_from_raw": "/Users/mf/.openclaw/workspace/knowledge-base/政策监控/戴总的政策文件（60部分清单）/40_煤电、气电、水电、核电、抽水蓄能、新型储能、氢能发电/_refetch_raw_20260427",
  "synced_at": "2026-04-27T20:10:38",
  "source_pdf_path": "/Users/mf/.openclaw/workspace/knowledge-base/政策监控/戴总的政策文件（60部分清单）/40_煤电、气电、水电、核电、抽水蓄能、新型储能、氢能发电/pdf/2021-11-03_发改运行〔2021〕1519号_关于开展全国煤电机组改造升级的通知.pdf",
  "source_json_path": "/Users/mf/.openclaw/workspace/knowledge-base/政策监控/戴总的政策文件（60部分清单）/40_煤电、气电、水电、核电、抽水蓄能、新型储能、氢能发电/json/2021-11-03_发改运行〔2021〕1519号_关于开展全国煤电机组改造升级的通知.json"
}