{
  "title": "关于深化燃煤发电上网电价形成机制改革的指导意见",
  "doc_no": "发改价格规〔2019〕1658号",
  "issuing_body": "",
  "signed_date": "2019-10-21",
  "published_date": "2019-10-22",
  "category": "47_电力价格、电价机制、输配电价、上网电价、销售电价",
  "official_html_url": "https://zfxxgk.ndrc.gov.cn/web/iteminfo.jsp?id=16530",
  "official_pdf_url": "https://zfxxgk.ndrc.gov.cn/upload/images/202210/20221021740481.pdf",
  "status": "ok",
  "method": "direct_pdf",
  "capture_profile": "",
  "crop_top_px": 0,
  "anchor_selector": "",
  "direct_pdf_error": "",
  "error": "",
  "generated_at": "2026-04-25T16:50:06.959335",
  "pdf_path": "/Users/mf/.openclaw/workspace/knowledge-base/政策监控/戴总的政策文件（60部分清单）/47_电力价格、电价机制、输配电价、上网电价、销售电价/pdf/2019-10-21_发改价格规〔2019〕1658号_关于深化燃煤发电上网电价形成机制改革的指导意见.pdf",
  "screenshot_path": "",
  "markdown_path": "",
  "size_bytes": 227228,
  "sha1": "e533d8e4b1b8e339d5cb48fe14798794dd57decc",
  "synced_from_theme": "06_电力改革 ／ 电力市场 ／ 辅助服务 ／ 现货市场",
  "synced_from_json": "/Users/mf/.openclaw/workspace/knowledge-base/政策监控/戴总的政策文件（60部分清单）/06_电力改革 ／ 电力市场 ／ 辅助服务 ／ 现货市场/json/2019-10-21_发改价格规〔2019〕1658号_关于深化燃煤发电上网电价形成机制改革的指导意见.json",
  "synced_at": "2026-04-27 19:53"
}