{
  "title": "“十四五”建筑节能与绿色建筑发展规划",
  "doc_no": "建标〔2022〕24号",
  "issuing_body": "住房城乡建设部",
  "signed_date": "2022-03-01",
  "published_date": "",
  "category": "60_电力需求侧管理、需求响应与能效提升",
  "official_html_url": "https://www.mohurd.gov.cn/gongkai/zc/wjk/art/2024/art_17339_765109.html",
  "official_pdf_url": "",
  "status": "ok",
  "method": "delivery_v3_browser_print_pdf",
  "capture_profile": "delivery_v3_browser_print_pdf",
  "crop_top_px": 0,
  "anchor_selector": "",
  "direct_pdf_error": "",
  "error": "",
  "generated_at": "2026-04-27T20:19:42.717794",
  "pdf_path": "/Users/mf/.openclaw/workspace/knowledge-base/政策监控/第六十批补抓：新增官方可核验去重3条/raw/2022-03-01_建标〔2022〕24号_“十四五”建筑节能与绿色建筑发展规划.pdf",
  "screenshot_path": "",
  "markdown_path": "",
  "size_bytes": 912451,
  "sha1": "628c3aa006446a809af13315ea37f72802d61dd0"
}