{
  "title": "国家能源局关于印发《电力市场信息披露基本规则》的通知",
  "doc_no": "国能发监管〔2024〕9号",
  "issuing_body": "国家能源局",
  "signed_date": "2024-01-31",
  "published_date": "",
  "category": "18_电力市场 ／ 中长期交易 ／ 现货市场 ／ 辅助服务市场 ／ 电力现货",
  "official_html_url": "https://zfxxgk.nea.gov.cn/2024-01/31/c_1310763726.htm",
  "official_pdf_url": "",
  "status": "ok",
  "method": "delivery_v3_browser_print_pdf",
  "capture_profile": "delivery_v3_browser_print_pdf",
  "crop_top_px": 0,
  "anchor_selector": "",
  "direct_pdf_error": "",
  "error": "",
  "generated_at": "2026-04-27T06:33:06.283705",
  "pdf_path": "/Users/mf/.openclaw/workspace/knowledge-base/政策监控/第十八批补抓：官方可核验20条/raw/2024-01-31_国能发监管〔2024〕9号_国家能源局关于印发《电力市场信息披露基本规则》的通知.pdf",
  "screenshot_path": "",
  "markdown_path": "",
  "size_bytes": 461117,
  "sha1": "d472fd55762e7da0aa122ae8cdac71b4eb5359f5"
}