{
  "title": "国家能源局关于印发《电力行业网络安全管理办法》的通知",
  "doc_no": "国能发安全规〔2022〕100号",
  "issuing_body": "国家能源局",
  "signed_date": "2022-11-16",
  "published_date": "",
  "category": "54_电力安全、电力监管、电力行政执法与行业监管",
  "official_html_url": "https://zfxxgk.nea.gov.cn/2022-11/16/c_1310683245.htm",
  "official_pdf_url": "",
  "status": "ok",
  "method": "delivery_v3_browser_print_pdf",
  "capture_profile": "delivery_v3_browser_print_pdf",
  "crop_top_px": 0,
  "anchor_selector": "",
  "direct_pdf_error": "",
  "error": "",
  "generated_at": "2026-04-27T18:48:21.000816",
  "pdf_path": "/Users/mf/.openclaw/workspace/knowledge-base/政策监控/戴总的政策文件（60部分清单）/54_电力安全、电力监管、电力行政执法与行业监管/pdf/2022-11-16_国能发安全规〔2022〕100号_国家能源局关于印发《电力行业网络安全管理办法》的通知.pdf",
  "screenshot_path": "",
  "markdown_path": "",
  "size_bytes": 426936,
  "sha1": "afe66af953d7a1f9ffbae51cc5e5d80d5775c5bd",
  "synced_from_raw": "/Users/mf/.openclaw/workspace/knowledge-base/政策监控/戴总的政策文件（60部分清单）/39_电力安全、电网调度、并网运行、供电可靠性、应急保供/_refetch_raw_20260427",
  "synced_at": "2026-04-27T20:10:38",
  "source_pdf_path": "/Users/mf/.openclaw/workspace/knowledge-base/政策监控/戴总的政策文件（60部分清单）/39_电力安全、电网调度、并网运行、供电可靠性、应急保供/pdf/2022-11-16_国能发安全规〔2022〕100号_国家能源局关于印发《电力行业网络安全管理办法》的通知.pdf",
  "source_json_path": "/Users/mf/.openclaw/workspace/knowledge-base/政策监控/戴总的政策文件（60部分清单）/39_电力安全、电网调度、并网运行、供电可靠性、应急保供/json/2022-11-16_国能发安全规〔2022〕100号_国家能源局关于印发《电力行业网络安全管理办法》的通知.json"
}