{
  "title": "关于建立健全可再生能源电力消纳保障机制的通知",
  "doc_no": "发改能源〔2019〕807号",
  "issuing_body": "国家发展改革委、国家能源局",
  "signed_date": "2019-05-10",
  "published_date": "",
  "category": "17_新能源消纳 ／ 消纳责任权重 ／ 保障性收购 ／ 跨省跨区消纳",
  "official_html_url": "https://www.ndrc.gov.cn/xxgk/zcfb/tz/201905/t20190515_962446.html",
  "official_pdf_url": "",
  "status": "ok",
  "method": "delivery_v3_browser_print_pdf",
  "capture_profile": "delivery_v3_browser_print_pdf",
  "crop_top_px": 0,
  "anchor_selector": "",
  "direct_pdf_error": "",
  "error": "",
  "generated_at": "2026-04-27T06:30:30.441418",
  "pdf_path": "/Users/mf/.openclaw/workspace/knowledge-base/政策监控/第十七批补抓：官方可核验20条/raw/2019-05-10_发改能源〔2019〕807号_关于建立健全可再生能源电力消纳保障机制的通知.pdf",
  "screenshot_path": "",
  "markdown_path": "",
  "size_bytes": 463346,
  "sha1": "d359702bcd52c643e4f8f52b9975cc2e8c10969b"
}