{
  "title": "关于印发《“十四五”新型储能发展实施方案》的通知",
  "doc_no": "发改能源〔2022〕209号",
  "issuing_body": "",
  "signed_date": "2022-01-29",
  "published_date": "2022-03-21",
  "category": "55_抽水蓄能、新型储能、储能参与电力市场与系统调节",
  "official_html_url": "https://www.ndrc.gov.cn/xxgk/zcfb/tz/202203/t20220321_1319772.html",
  "official_pdf_url": "",
  "status": "ok",
  "method": "delivery_v3_browser_print_pdf",
  "capture_profile": "delivery_v3_browser_print_pdf",
  "crop_top_px": 0,
  "anchor_selector": "",
  "direct_pdf_error": "",
  "error": "",
  "generated_at": "2026-04-27T18:48:14.915183",
  "pdf_path": "/Users/mf/.openclaw/workspace/knowledge-base/政策监控/戴总的政策文件（60部分清单）/55_抽水蓄能、新型储能、储能参与电力市场与系统调节/pdf/2022-01-29_发改能源〔2022〕209号_关于印发《“十四五”新型储能发展实施方案》的通知.pdf",
  "screenshot_path": "",
  "markdown_path": "",
  "size_bytes": 193355,
  "sha1": "ca84cfad37e1d2b3d2268bb1d6e8cb2a06833ba0",
  "synced_from_raw": "/Users/mf/.openclaw/workspace/knowledge-base/政策监控/戴总的政策文件（60部分清单）/40_煤电、气电、水电、核电、抽水蓄能、新型储能、氢能发电/_refetch_raw_20260427",
  "synced_at": "2026-04-27T20:10:38",
  "source_pdf_path": "/Users/mf/.openclaw/workspace/knowledge-base/政策监控/戴总的政策文件（60部分清单）/40_煤电、气电、水电、核电、抽水蓄能、新型储能、氢能发电/pdf/2022-01-29_发改能源〔2022〕209号_关于印发《“十四五”新型储能发展实施方案》的通知.pdf",
  "source_json_path": "/Users/mf/.openclaw/workspace/knowledge-base/政策监控/戴总的政策文件（60部分清单）/40_煤电、气电、水电、核电、抽水蓄能、新型储能、氢能发电/json/2022-01-29_发改能源〔2022〕209号_关于印发《“十四五”新型储能发展实施方案》的通知.json"
}