[
  {
    "id": "GB/Z",
    "name": "120.305-2026 微电网 第3-5部分：微电网监控及能量管理系统测试",
    "url": "https://www.bzfxw.com/soft/sort055/sort063/1103154.html"
  },
  {
    "id": "DL/T",
    "name": "2780-2024 110kV 及以上交联聚乙烯绝缘交流海底电缆耐压同步局部放电试验导则",
    "url": "https://www.bzfxw.com/soft/sort055/sort063/1069173.html"
  },
  {
    "id": "NB/T",
    "name": "11496-2024 柔性直流换流阀子模块损耗测试方法",
    "url": "https://www.bzfxw.com/soft/sort055/sort063/1067836.html"
  },
  {
    "id": "T/CERS",
    "name": "0029-2024 综合能源系统信息模型技术指引",
    "url": "https://www.bzfxw.com/soft/sort055/nengyuan/1041901.html"
  },
  {
    "id": "T/CECA-G",
    "name": "0320-2024 综合能源规划设计负荷分析技术规范",
    "url": "https://www.bzfxw.com/soft/sort055/nengyuan/1041884.html"
  }
]